README.rst
setup.cfg
setup.py
muextensions/__init__.py
muextensions/version.py
muextensions.egg-info/PKG-INFO
muextensions.egg-info/SOURCES.txt
muextensions.egg-info/dependency_links.txt
muextensions.egg-info/requires.txt
muextensions.egg-info/top_level.txt
muextensions/connector/__init__.py
muextensions/connector/docutils/__init__.py
muextensions/connector/docutils/ditaa.py
muextensions/connector/docutils/plantuml.py
muextensions/contrib/__init__.py
muextensions/contrib/hovercraft.py
muextensions/contrib/pelican.py
muextensions/executor/__init__.py
muextensions/executor/ditaa.py
muextensions/executor/plantuml.py
tests/connector/__init__.py
tests/connector/docutils/__init__.py
tests/connector/docutils/test_ditaa.py
tests/connector/docutils/test_plantuml.py
tests/contrib/__init__.py
tests/contrib/test_hovercraft.py
tests/contrib/test_pelican.py