Metadata-Version: 2.1
Name: muextensions
Version: 0.0.17
Summary: Markup extentions
Home-page: https://github.com/pedrohdz/muextensions
Author: Pedro H.
Author-email: 5179251+pedrohdz@users.noreply.github.com
License: Apache License 2.0
Keywords: pelican hovercraft plantuml uml docutils
Platform: UNKNOWN
Classifier: Development Status :: 3 - Alpha
Classifier: License :: OSI Approved :: Apache Software License
Classifier: Programming Language :: Python :: 3 :: Only
Classifier: Programming Language :: Python :: 3.5
Classifier: Programming Language :: Python :: 3.6
Classifier: Programming Language :: Python :: 3.7
Classifier: Topic :: Documentation
Provides-Extra: ci
Provides-Extra: test
